[
  {
    "id": "issuekey",
    "name": "Код",
    "custom": false,
    "orderable": false,
    "navigable": true,
    "searchable": false,
    "clauseNames": [
      "id",
      "issue",
      "issuekey",
      "key"
    ]
  },
  {
    "id": "timespent",
    "name": "Затраченное время",
    "custom": false,
    "orderable": false,
    "navigable": true,
    "searchable": false,
    "clauseNames": [
      "timespent"
    ],
    "schema": {
      "type": "number",
      "system": "timespent"
    }
  },
  {
    "id": "timeoriginalestimate",
    "name": "Первоначальная оценка",
    "custom": false,
    "orderable": false,
    "navigable": true,
    "searchable": false,
    "clauseNames": [
      "originalEstimate",
      "timeoriginalestimate"
    ],
    "schema": {
      "type": "number",
      "system": "timeoriginalestimate"
    }
  },
  {
    "id": "project",
    "name": "Проект",
    "custom": false,
    "orderable": false,
    "navigable": true,
    "searchable": true,
    "clauseNames": [
      "project"
    ],
    "schema": {
      "type": "project",
      "system": "project"
    }
  },
  {
    "id": "aggregatetimespent",
    "name": "Суммарное затраченое время",
    "custom": false,
    "orderable": false,
    "navigable": true,
    "searchable": false,
    "clauseNames": [],
    "schema": {
      "type": "number",
      "system": "aggregatetimespent"
    }
  },
  {
    "id": "timetracking",
    "name": "Учет времени",
    "custom": false,
    "orderable": true,
    "navigable": false,
    "searchable": true,
    "clauseNames": [],
    "schema": {
      "type": "timetracking",
      "system": "timetracking"
    }
  },
  {
    "id": "attachment",
    "name": "Вложение",
    "custom": false,
    "orderable": true,
    "navigable": false,
    "searchable": true,
    "clauseNames": [
      "attachments"
    ],
    "schema": {
      "type": "array",
      "items": "attachment",
      "system": "attachment"
    }
  },
  {
    "id": "aggregatetimeestimate",
    "name": "Суммарное оставшееся время",
    "custom": false,
    "orderable": false,
    "navigable": true,
    "searchable": false,
    "clauseNames": [],
    "schema": {
      "type": "number",
      "system": "aggregatetimeestimate"
    }
  },
  {
    "id": "resolutiondate",
    "name": "Дата решения",
    "custom": false,
    "orderable": false,
    "navigable": true,
    "searchable": true,
    "clauseNames": [
      "resolutiondate",
      "resolved"
    ],
    "schema": {
      "type": "datetime",
      "system": "resolutiondate"
    }
  },
  {
    "id": "workratio",
    "name": "КПД (полезная работа/затраченная работа)",
    "custom": false,
    "orderable": false,
    "navigable": true,
    "searchable": true,
    "clauseNames": [
      "workratio"
    ],
    "schema": {
      "type": "number",
      "system": "workratio"
    }
  },
  {
    "id": "lastViewed",
    "name": "Последний просмотр",
    "custom": false,
    "orderable": false,
    "navigable": true,
    "searchable": false,
    "clauseNames": [
      "lastViewed"
    ],
    "schema": {
      "type": "datetime",
      "system": "lastViewed"
    }
  },
  {
    "id": "watches",
    "name": "Наблюдатели",
    "custom": false,
    "orderable": false,
    "navigable": true,
    "searchable": false,
    "clauseNames": [
      "watchers"
    ],
    "schema": {
      "type": "watches",
      "system": "watches"
    }
  },
  {
    "id": "creator",
    "name": "Создатель",
    "custom": false,
    "orderable": false,
    "navigable": true,
    "searchable": true,
    "clauseNames": [
      "creator"
    ],
    "schema": {
      "type": "user",
      "system": "creator"
    }
  },
  {
    "id": "thumbnail",
    "name": "Изображения",
    "custom": false,
    "orderable": false,
    "navigable": true,
    "searchable": false,
    "clauseNames": []
  },
  {
    "id": "subtasks",
    "name": "Подзадачи",
    "custom": false,
    "orderable": false,
    "navigable": true,
    "searchable": false,
    "clauseNames": [
      "subtasks"
    ],
    "schema": {
      "type": "array",
      "items": "issuelinks",
      "system": "subtasks"
    }
  },
  {
    "id": "created",
    "name": "Cоздано",
    "custom": false,
    "orderable": false,
    "navigable": true,
    "searchable": true,
    "clauseNames": [
      "created",
      "createdDate"
    ],
    "schema": {
      "type": "datetime",
      "system": "created"
    }
  },
  {
    "id": "aggregateprogress",
    "name": "Суммарный прогресс",
    "custom": false,
    "orderable": false,
    "navigable": true,
    "searchable": false,
    "clauseNames": [],
    "schema": {
      "type": "progress",
      "system": "aggregateprogress"
    }
  },
  {
    "id": "aggregatetimeoriginalestimate",
    "name": "Суммарная первоначальная оценка",
    "custom": false,
    "orderable": false,
    "navigable": true,
    "searchable": false,
    "clauseNames": [],
    "schema": {
      "type": "number",
      "system": "aggregatetimeoriginalestimate"
    }
  },
  {
    "id": "timeestimate",
    "name": "Оставшееся время",
    "custom": false,
    "orderable": false,
    "navigable": true,
    "searchable": false,
    "clauseNames": [
      "remainingEstimate",
      "timeestimate"
    ],
    "schema": {
      "type": "number",
      "system": "timeestimate"
    }
  },
  {
    "id": "progress",
    "name": "Прогресс",
    "custom": false,
    "orderable": false,
    "navigable": true,
    "searchable": false,
    "clauseNames": [
      "progress"
    ],
    "schema": {
      "type": "progress",
      "system": "progress"
    }
  },
  {
    "id": "comment",
    "name": "Комментарий",
    "custom": false,
    "orderable": true,
    "navigable": false,
    "searchable": true,
    "clauseNames": [
      "comment"
    ],
    "schema": {
      "type": "comments-page",
      "system": "comment"
    }
  },
  {
    "id": "votes",
    "name": "Голоса",
    "custom": false,
    "orderable": false,
    "navigable": true,
    "searchable": false,
    "clauseNames": [
      "votes"
    ],
    "schema": {
      "type": "votes",
      "system": "votes"
    }
  },
  {
    "id": "worklog",
    "name": "Сделать запись о работе",
    "custom": false,
    "orderable": true,
    "navigable": false,
    "searchable": true,
    "clauseNames": [],
    "schema": {
      "type": "array",
      "items": "worklog",
      "system": "worklog"
    }
  },
  {
    "id": "updated",
    "name": "Обновленo",
    "custom": false,
    "orderable": false,
    "navigable": true,
    "searchable": true,
    "clauseNames": [
      "updated",
      "updatedDate"
    ],
    "schema": {
      "type": "datetime",
      "system": "updated"
    }
  },
  {
    "id": "status",
    "name": "Статус",
    "custom": false,
    "orderable": false,
    "navigable": true,
    "searchable": true,
    "clauseNames": [
      "status"
    ],
    "schema": {
      "type": "status",
      "system": "status"
    }
  }
]